{"type": "FeatureCollection", "features": [{"type": "Feature", "geometry": {"type": "Polygon", "coordinates": [[[65.582794, 51.373882], [65.487404, 51.271294], [65.02668, 51.354874], [65.102654, 51.649204], [64.852509, 51.972099], [64.728195, 52.163403], [64.818016, 52.579792], [65.148621, 53.149086], [65.294067, 53.066521], [66.11039, 52.996765], [66.052933, 52.40218], [65.837219, 51.830608], [65.574417, 51.746964], [65.582794, 51.373882]]]}, "properties": {"GID_0": "KAZ", "NAME_0": "Kazakhstan", "GID_1": "KAZ.10_1", "NAME_1": "Qostanay", "NL_NAME_1": "", "GID_2": "KAZ.10.10_1", "NAME_2": "Karasuskiy", "VARNAME_2": "", "NL_NAME_2": "", "TYPE_2": "Rayon", "ENGTYPE_2": "District", "CC_2": "", "HASC_2": "KZ.QS.KS"}}]}