{"type": "FeatureCollection", "features": [{"type": "Feature", "geometry": {"type": "Polygon", "coordinates": [[[34.633263, 49.630638], [34.659939, 49.624363], [34.65757, 49.576759], [34.637836, 49.541283], [34.601025, 49.523888], [34.556084, 49.524452], [34.530518, 49.554523], [34.477596, 49.578968], [34.579842, 49.643181], [34.633263, 49.630638]]]}, "properties": {"GID_0": "UKR", "NAME_0": "Ukraine", "GID_1": "UKR.18_1", "NAME_1": "Poltava", "NL_NAME_1": "", "GID_2": "UKR.18.22_1", "NAME_2": "Poltavs'ka", "VARNAME_2": "Poltava", "NL_NAME_2": "", "TYPE_2": "Misto", "ENGTYPE_2": "City", "CC_2": "", "HASC_2": "UA.PL.PM"}}]}