{"type": "FeatureCollection", "features": [{"type": "Feature", "geometry": {"type": "Polygon", "coordinates": [[[55.03986, 25.899305], [55.057919, 25.862362], [55.032082, 25.855139], [55.009583, 25.876806], [55.03986, 25.899305]]]}, "properties": {"GID_0": "IRN", "NAME_0": "Iran", "GID_1": "IRN.11_1", "NAME_1": "Hormozgan", "NL_NAME_1": "", "GID_2": "IRN.11.1_1", "NAME_2": "Abu Musa", "VARNAME_2": "", "NL_NAME_2": "", "TYPE_2": "Shahrestan", "ENGTYPE_2": "County", "CC_2": "", "HASC_2": "IR.HG.AB"}}]}