{"type": "FeatureCollection", "features": [{"type": "Feature", "geometry": {"type": "Polygon", "coordinates": [[[-99.004471, 19.60375], [-99.020462, 19.589178], [-99.035767, 19.555321], [-99.057457, 19.530149], [-99.073921, 19.5233], [-99.078362, 19.534121], [-99.069366, 19.551651], [-99.067451, 19.583851], [-99.052086, 19.599581], [-99.013367, 19.615419], [-99.009712, 19.619101], [-99.004471, 19.60375]]]}, "properties": {"GID_0": "MEX", "NAME_0": "Mexico", "GID_1": "MEX.15_1", "NAME_1": "M\u00e9xico", "NL_NAME_1": "", "GID_2": "MEX.15.27_1", "NAME_2": "Coacalco de Berrioz\u00e1bal", "VARNAME_2": "Coacalco", "NL_NAME_2": "", "TYPE_2": "Municipio", "ENGTYPE_2": "Municipality", "CC_2": "", "HASC_2": "MX.MX.CB"}}]}