{"type": "FeatureCollection", "features": [{"type": "Feature", "geometry": {"type": "Polygon", "coordinates": [[[-98.724167, 18.99432], [-98.73056, 19.016941], [-98.746368, 19.02459], [-98.74781, 19.050961], [-98.727539, 19.060013], [-98.69471, 19.046322], [-98.692497, 19.038172], [-98.699463, 19.00663], [-98.704407, 18.997892], [-98.724167, 18.99432]]]}, "properties": {"GID_0": "MEX", "NAME_0": "Mexico", "GID_1": "MEX.15_1", "NAME_1": "M\u00e9xico", "NL_NAME_1": "", "GID_2": "MEX.15.70_1", "NAME_2": "Ozumba", "VARNAME_2": "", "NL_NAME_2": "", "TYPE_2": "Municipio", "ENGTYPE_2": "Municipality", "CC_2": "", "HASC_2": "MX.MX.OZ"}}]}