{"type": "FeatureCollection", "features": [{"type": "Feature", "geometry": {"type": "Polygon", "coordinates": [[[37.626717, 40.881081], [37.582401, 40.832588], [37.525791, 40.840229], [37.493584, 40.876999], [37.464314, 40.900505], [37.504402, 40.920876], [37.573792, 40.922325], [37.596088, 40.920486], [37.61385, 40.908974], [37.626717, 40.881081]]]}, "properties": {"GID_0": "TUR", "NAME_0": "Turkey", "GID_1": "TUR.63_1", "NAME_1": "Ordu", "NL_NAME_1": "", "GID_2": "TUR.63.3_1", "NAME_2": "\u00c7ama\u015f", "VARNAME_2": "", "NL_NAME_2": "", "TYPE_2": "District", "ENGTYPE_2": "District", "CC_2": "", "HASC_2": "TR.OR.CM"}}]}