{"type": "FeatureCollection", "features": [{"type": "Feature", "geometry": {"type": "Polygon", "coordinates": [[[-92.288307, 46.667889], [-92.289017, 46.593609], [-92.289169, 46.41758], [-92.359268, 46.417709], [-93.05275, 46.41901], [-93.053551, 46.593189], [-93.060806, 46.593681], [-93.062256, 46.673931], [-93.060333, 46.767029], [-92.731697, 46.767422], [-92.665428, 46.769329], [-92.597206, 46.76659], [-92.481926, 46.766712], [-92.299103, 46.765232], [-92.29628, 46.66613], [-92.288307, 46.667889]]]}, "properties": {"GID_0": "USA", "NAME_0": "United States", "GID_1": "USA.24_1", "NAME_1": "Minnesota", "NL_NAME_1": "", "GID_2": "USA.24.9_1", "NAME_2": "Carlton", "VARNAME_2": "", "NL_NAME_2": "", "TYPE_2": "County", "ENGTYPE_2": "County", "CC_2": "", "HASC_2": "US.MN.CL"}}]}