{"type": "FeatureCollection", "features": [{"type": "Feature", "geometry": {"type": "Polygon", "coordinates": [[[-100.237747, 32.08234], [-100.235359, 32.003479], [-100.234436, 31.69199], [-100.825363, 31.696489], [-100.8153, 32.08511], [-100.669807, 32.08379], [-100.237747, 32.08234]]]}, "properties": {"GID_0": "USA", "NAME_0": "United States", "GID_1": "USA.44_1", "NAME_1": "Texas", "NL_NAME_1": "", "GID_2": "USA.44.41_1", "NAME_2": "Coke", "VARNAME_2": "", "NL_NAME_2": "", "TYPE_2": "County", "ENGTYPE_2": "County", "CC_2": "", "HASC_2": "US.TX.OK"}}]}