{"type": "FeatureCollection", "features": [{"type": "Feature", "geometry": {"type": "Polygon", "coordinates": [[[-99.603073, 29.906759], [-99.690758, 29.907949], [-99.691513, 29.957479], [-99.692253, 30.07749], [-99.757668, 30.077202], [-99.757576, 30.288151], [-99.303223, 30.288952], [-99.303421, 30.139778], [-98.9217, 30.138981], [-98.925278, 29.784191], [-99.176567, 29.89456], [-99.283867, 29.904961], [-99.603073, 29.906759]]]}, "properties": {"GID_0": "USA", "NAME_0": "United States", "GID_1": "USA.44_1", "NAME_1": "Texas", "NL_NAME_1": "", "GID_2": "USA.44.133_1", "NAME_2": "Kerr", "VARNAME_2": "", "NL_NAME_2": "", "TYPE_2": "County", "ENGTYPE_2": "County", "CC_2": "", "HASC_2": "US.TX.KR"}}]}