{"type": "FeatureCollection", "features": [{"type": "Feature", "geometry": {"type": "Polygon", "coordinates": [[[-96.323647, 31.359261], [-96.594818, 31.223511], [-96.799957, 31.519161], [-96.932877, 31.71142], [-96.718437, 31.81945], [-96.499756, 31.80052], [-96.429771, 31.70109], [-96.233261, 31.411522], [-96.3228, 31.366081], [-96.323647, 31.359261]]]}, "properties": {"GID_0": "USA", "NAME_0": "United States", "GID_1": "USA.44_1", "NAME_1": "Texas", "NL_NAME_1": "", "GID_2": "USA.44.147_1", "NAME_2": "Limestone", "VARNAME_2": "", "NL_NAME_2": "", "TYPE_2": "County", "ENGTYPE_2": "County", "CC_2": "", "HASC_2": "US.TX.LO"}}]}