{"type": "FeatureCollection", "features": [{"type": "Feature", "geometry": {"type": "Polygon", "coordinates": [[[-97.961037, 47.240959], [-97.961746, 47.326019], [-97.986473, 47.326469], [-97.987816, 47.673801], [-97.883636, 47.674179], [-97.599449, 47.672661], [-97.474426, 47.67321], [-97.475128, 47.58577], [-97.474487, 47.498329], [-97.472473, 47.325352], [-97.451767, 47.32489], [-97.450417, 47.239349], [-97.706078, 47.24017], [-97.961037, 47.240959]]]}, "properties": {"GID_0": "USA", "NAME_0": "United States", "GID_1": "USA.35_1", "NAME_1": "North Dakota", "NL_NAME_1": "", "GID_2": "USA.35.46_1", "NAME_2": "Steele", "VARNAME_2": "", "NL_NAME_2": "", "TYPE_2": "County", "ENGTYPE_2": "County", "CC_2": "", "HASC_2": "US.ND.SE"}}]}