{"type": "FeatureCollection", "features": [{"type": "Feature", "geometry": {"type": "Polygon", "coordinates": [[[-66.967133, 10.408032], [-66.913849, 10.427377], [-66.889763, 10.43225], [-66.880089, 10.41675], [-66.874001, 10.39046], [-66.863007, 10.38956], [-66.861931, 10.376792], [-66.905548, 10.390271], [-66.91658, 10.386729], [-66.926048, 10.368013], [-66.941811, 10.369538], [-66.949135, 10.376366], [-66.967133, 10.408032]]]}, "properties": {"GID_0": "VEN", "NAME_0": "Venezuela", "GID_1": "VEN.16_1", "NAME_1": "Miranda", "NL_NAME_1": "", "GID_2": "VEN.16.13_1", "NAME_2": "Los Salias", "VARNAME_2": "", "NL_NAME_2": "", "TYPE_2": "Municipio", "ENGTYPE_2": "Municipality", "CC_2": "", "HASC_2": ""}}]}