{"type": "FeatureCollection", "features": [{"type": "Feature", "geometry": {"type": "Polygon", "coordinates": [[[16.390701, 46.389866], [16.401962, 46.385674], [16.410362, 46.376873], [16.411385, 46.37056], [16.419493, 46.357399], [16.428186, 46.35685], [16.431534, 46.351704], [16.414886, 46.342865], [16.409548, 46.346382], [16.394432, 46.351349], [16.392191, 46.371174], [16.388901, 46.379642], [16.390701, 46.389866]]]}, "properties": {"GID_0": "HRV", "NAME_0": "Croatia", "GID_1": "HRV.10_1", "NAME_1": "Medimurska", "NL_NAME_1": "", "GID_2": "HRV.10.20_1", "NAME_2": "Strahoninec", "VARNAME_2": "", "NL_NAME_2": "", "TYPE_2": "", "ENGTYPE_2": "", "CC_2": "", "HASC_2": ""}}]}