{"type": "FeatureCollection", "features": [{"type": "Feature", "geometry": {"type": "Polygon", "coordinates": [[[105.06543, 10.61088], [105.024475, 10.66455], [105.023621, 10.677694], [105.098007, 10.720841], [105.088325, 10.760432], [105.124573, 10.709785], [105.144646, 10.704729], [105.155487, 10.701854], [105.152931, 10.686663], [105.081543, 10.614613], [105.06543, 10.61088]]]}, "properties": {"GID_0": "VNM", "NAME_0": "Vietnam", "GID_1": "VNM.1_1", "NAME_1": "An Giang", "NL_NAME_1": "", "GID_2": "VNM.1.3_1", "NAME_2": "Ch\u00e2u \u0110\u1ed1c", "VARNAME_2": "Chau Doc", "NL_NAME_2": "", "TYPE_2": "Th\u00e0nh ph\u1ed1", "ENGTYPE_2": "City", "CC_2": "", "HASC_2": "VN.KG.AB"}}]}