{"type": "FeatureCollection", "features": [{"type": "Feature", "geometry": {"type": "Polygon", "coordinates": [[[105.724869, 20.955395], [105.699127, 20.978004], [105.665733, 20.985035], [105.677055, 21.018967], [105.650803, 21.043985], [105.663643, 21.065531], [105.685738, 21.089718], [105.717331, 21.071714], [105.729454, 21.056561], [105.739113, 21.025188], [105.735283, 20.996582], [105.741455, 20.96806], [105.724869, 20.955395]]]}, "properties": {"GID_0": "VNM", "NAME_0": "Vietnam", "GID_1": "VNM.27_1", "NAME_1": "H\u00e0 N\u1ed9i", "NL_NAME_1": "", "GID_2": "VNM.27.13_1", "NAME_2": "Ho\u00e0i \u0110\u1ee9c", "VARNAME_2": "Hoai Duc", "NL_NAME_2": "", "TYPE_2": "Huy\u1ec7n", "ENGTYPE_2": "District", "CC_2": "", "HASC_2": "VN.BU.HT"}}]}