{"type": "FeatureCollection", "features": [{"type": "Feature", "geometry": {"type": "Polygon", "coordinates": [[[106.66687, 10.78962], [106.672798, 10.814128], [106.68399, 10.809969], [106.691612, 10.795526], [106.686134, 10.79252], [106.66687, 10.78962]]]}, "properties": {"GID_0": "VNM", "NAME_0": "Vietnam", "GID_1": "VNM.25_1", "NAME_1": "H\u1ed3 Ch\u00ed Minh", "NL_NAME_1": "", "GID_2": "VNM.25.9_1", "NAME_2": "Ph\u00fa Nhu\u1eadn", "VARNAME_2": "Phu Nhuan", "NL_NAME_2": "", "TYPE_2": "Qu\u1eadn", "ENGTYPE_2": "Urban District", "CC_2": "", "HASC_2": "VN.HO.KS"}}]}