{"type": "FeatureCollection", "features": [{"type": "Feature", "geometry": {"type": "Polygon", "coordinates": [[[-89.222946, 14.350768], [-89.198196, 14.35168], [-89.191261, 14.3555], [-89.176208, 14.343448], [-89.154236, 14.337216], [-89.140617, 14.336975], [-89.1521, 14.31853], [-89.168037, 14.328303], [-89.17733, 14.32384], [-89.207138, 14.324946], [-89.217239, 14.33065], [-89.21727, 14.345588], [-89.222946, 14.350768]]]}, "properties": {"GID_0": "SLV", "NAME_0": "El Salvador", "GID_1": "SLV.3_1", "NAME_1": "Chalatenango", "NL_NAME_1": "", "GID_2": "SLV.3.26_1", "NAME_2": "San Ignacio", "VARNAME_2": "", "NL_NAME_2": "", "TYPE_2": "Municipio", "ENGTYPE_2": "Municipality", "CC_2": "", "HASC_2": "SV.CH.SI"}}]}