{"type": "FeatureCollection", "features": [{"type": "Feature", "geometry": {"type": "Polygon", "coordinates": [[[133.846695, 34.598927], [133.833801, 34.592175], [133.819061, 34.59388], [133.810806, 34.600361], [133.810684, 34.611877], [133.821213, 34.621826], [133.834656, 34.62204], [133.8461, 34.618126], [133.846695, 34.598927]]]}, "properties": {"GID_0": "JPN", "NAME_0": "Japan", "GID_1": "JPN.31_1", "NAME_1": "Okayama", "NL_NAME_1": "\u5ca1\u5c71\u770c", "GID_2": "JPN.31.4_1", "NAME_2": "Hayashima", "VARNAME_2": "", "NL_NAME_2": "\u65e9\u5cf6\u753a", "TYPE_2": "Machi", "ENGTYPE_2": "Town", "CC_2": "", "HASC_2": ""}}]}