{"type": "FeatureCollection", "features": [{"type": "Feature", "geometry": {"type": "Polygon", "coordinates": [[[133.80806, 34.307194], [133.807556, 34.313931], [133.827087, 34.321392], [133.835678, 34.315113], [133.839752, 34.306999], [133.837097, 34.28614], [133.80806, 34.307194]]]}, "properties": {"GID_0": "JPN", "NAME_0": "Japan", "GID_1": "JPN.17_1", "NAME_1": "Kagawa", "NL_NAME_1": "\u9999\u5ddd\u770c", "GID_2": "JPN.17.13_1", "NAME_2": "Utazu", "VARNAME_2": "", "NL_NAME_2": "\u5b87\u591a\u6d25\u753a", "TYPE_2": "Machi", "ENGTYPE_2": "Town", "CC_2": "", "HASC_2": ""}}]}