{"type": "FeatureCollection", "features": [{"type": "Feature", "geometry": {"type": "Polygon", "coordinates": [[[-86.045105, 11.909812], [-86.05925, 11.906967], [-86.077888, 11.888921], [-86.093285, 11.904073], [-86.083763, 11.914951], [-86.058296, 11.926415], [-86.040337, 11.922003], [-86.045105, 11.909812]]]}, "properties": {"GID_0": "NIC", "NAME_0": "Nicaragua", "GID_1": "NIC.14_1", "NAME_1": "Masaya", "NL_NAME_1": "", "GID_2": "NIC.14.1_1", "NAME_2": "Catarina", "VARNAME_2": "", "NL_NAME_2": "", "TYPE_2": "Municipio", "ENGTYPE_2": "Municipality", "CC_2": "", "HASC_2": "NI.MS.CA"}}]}