{"type": "FeatureCollection", "features": [{"type": "Feature", "geometry": {"type": "Polygon", "coordinates": [[[-86.085419, 11.82877], [-86.072464, 11.871053], [-86.069748, 11.875652], [-86.054596, 11.897249], [-86.048134, 11.89066], [-86.02449, 11.885418], [-86.034233, 11.871333], [-86.058769, 11.863256], [-86.055626, 11.834345], [-86.058067, 11.823824], [-86.078293, 11.819455], [-86.088127, 11.824349], [-86.085419, 11.82877]]]}, "properties": {"GID_0": "NIC", "NAME_0": "Nicaragua", "GID_1": "NIC.8_1", "NAME_1": "Granada", "NL_NAME_1": "", "GID_2": "NIC.8.1_1", "NAME_2": "Diri\u00e1", "VARNAME_2": "Diri", "NL_NAME_2": "", "TYPE_2": "Municipio", "ENGTYPE_2": "Municipality", "CC_2": "", "HASC_2": "NI.GR.DA"}}]}