{"type": "FeatureCollection", "features": [{"type": "Feature", "geometry": {"type": "Polygon", "coordinates": [[[48.922504, 38.914227], [48.902866, 38.889332], [48.793606, 38.874081], [48.671753, 38.826771], [48.59343, 38.867191], [48.547623, 38.939865], [48.477772, 38.985737], [48.53796, 38.995296], [48.576786, 39.042561], [48.663929, 39.082462], [48.661098, 39.135262], [48.740498, 39.147236], [48.85442, 39.131641], [48.851196, 39.060474], [48.922504, 38.914227]]]}, "properties": {"GID_0": "AZE", "NAME_0": "Azerbaijan", "GID_1": "AZE.6_1", "NAME_1": "Lankaran", "NL_NAME_1": "", "GID_2": "AZE.6.6_1", "NAME_2": "Masall\u0131", "VARNAME_2": "Masally", "NL_NAME_2": "", "TYPE_2": "Rayon", "ENGTYPE_2": "District", "CC_2": "", "HASC_2": "AZ.MA"}}]}