{"type": "FeatureCollection", "features": [{"type": "Feature", "geometry": {"type": "Polygon", "coordinates": [[[45.121109, 41.355663], [45.271866, 41.288704], [45.376472, 41.27224], [45.404537, 41.228497], [45.363873, 41.107521], [45.37991, 41.019398], [45.318283, 41.003151], [45.193451, 41.071743], [45.088505, 41.083668], [45.084858, 41.114693], [45.178337, 41.131561], [45.130581, 41.208984], [45.01738, 41.194054], [45.0448, 41.251427], [45.004055, 41.301422], [45.121109, 41.355663]]]}, "properties": {"GID_0": "AZE", "NAME_0": "Azerbaijan", "GID_1": "AZE.4_1", "NAME_1": "Ganja-Qazakh", "NL_NAME_1": "", "GID_2": "AZE.4.7_1", "NAME_2": "Qazax", "VARNAME_2": "Qazakh", "NL_NAME_2": "", "TYPE_2": "Rayon", "ENGTYPE_2": "District", "CC_2": "", "HASC_2": "AZ.QZ"}}]}