{"type": "FeatureCollection", "features": [{"type": "Feature", "geometry": {"type": "Polygon", "coordinates": [[[72.28968, 40.831219], [72.242599, 40.818962], [72.162186, 40.831158], [72.113937, 40.885143], [72.109131, 40.904049], [72.163582, 40.953899], [72.201485, 41.002571], [72.281921, 41.025833], [72.30233, 40.984222], [72.352173, 40.93417], [72.423248, 40.949429], [72.432388, 40.900665], [72.341537, 40.866665], [72.28968, 40.831219]]]}, "properties": {"GID_0": "UZB", "NAME_0": "Uzbekistan", "GID_1": "UZB.1_1", "NAME_1": "Andijon", "NL_NAME_1": "", "GID_2": "UZB.1.6_1", "NAME_2": "Izboskan", "VARNAME_2": "Izboskan", "NL_NAME_2": "", "TYPE_2": "District", "ENGTYPE_2": "District", "CC_2": "", "HASC_2": "UZ.AN.IZ"}}]}