{"type": "FeatureCollection", "features": [{"type": "Feature", "geometry": {"type": "Polygon", "coordinates": [[[69.695427, 41.112835], [69.626617, 41.07272], [69.563255, 41.111469], [69.46138, 41.113411], [69.46405, 41.133289], [69.39473, 41.16827], [69.377853, 41.223507], [69.343246, 41.245129], [69.426926, 41.244709], [69.51004, 41.305431], [69.573662, 41.296272], [69.558838, 41.213619], [69.650223, 41.21133], [69.666847, 41.171104], [69.626915, 41.102329], [69.695427, 41.112835]]]}, "properties": {"GID_0": "UZB", "NAME_0": "Uzbekistan", "GID_1": "UZB.14_1", "NAME_1": "Tashkent", "NL_NAME_1": "", "GID_2": "UZB.14.14_1", "NAME_2": "Yuqorichirchiq", "VARNAME_2": "Yukori Chirchiq", "NL_NAME_2": "", "TYPE_2": "District", "ENGTYPE_2": "District", "CC_2": "", "HASC_2": "UZ.TA.YU"}}]}