{"type": "FeatureCollection", "features": [{"type": "Feature", "geometry": {"type": "Polygon", "coordinates": [[[5.281078, 36.593613], [5.260331, 36.587307], [5.255129, 36.596649], [5.237923, 36.611488], [5.233253, 36.631371], [5.221055, 36.639851], [5.206336, 36.629478], [5.196544, 36.627071], [5.192344, 36.634178], [5.213548, 36.65097], [5.249584, 36.640694], [5.286993, 36.63736], [5.284739, 36.614639], [5.288864, 36.599514], [5.281078, 36.593613]]]}, "properties": {"GID_0": "DZA", "NAME_0": "Algeria", "GID_1": "DZA.8_1", "NAME_1": "B\u00e9ja\u00efa", "NL_NAME_1": "\u0628\u062c\u0627\u064a\u0629", "GID_2": "DZA.8.8_1", "NAME_2": "Aokas", "VARNAME_2": "", "NL_NAME_2": "", "TYPE_2": "Commune-Cotiere", "ENGTYPE_2": "Commune-Cotiere", "CC_2": "622", "HASC_2": "DZ.BJ.AO"}}]}