{"type": "FeatureCollection", "features": [{"type": "Feature", "geometry": {"type": "Polygon", "coordinates": [[[2.934528, 36.705856], [2.917975, 36.718811], [2.912154, 36.735954], [2.928959, 36.747097], [2.971652, 36.741474], [2.961972, 36.720352], [2.966202, 36.706642], [2.948822, 36.701588], [2.934528, 36.705856]]]}, "properties": {"GID_0": "DZA", "NAME_0": "Algeria", "GID_1": "DZA.4_1", "NAME_1": "Alger", "NL_NAME_1": "\u0648\u0644\u0627\u064a\u0629 \u0627\u0644\u062c\u0632\u0627\u0626\u0631", "GID_2": "DZA.4.18_1", "NAME_2": "Ouled Fayet", "VARNAME_2": "", "NL_NAME_2": "", "TYPE_2": "Commune", "ENGTYPE_2": "Commune", "CC_2": "1651", "HASC_2": "DZ.AL.OF"}}]}