{"type": "FeatureCollection", "features": [{"type": "Feature", "geometry": {"type": "Polygon", "coordinates": [[[3.936435, 7.338191], [3.904278, 7.314429], [3.874187, 7.313754], [3.877523, 7.328936], [3.901587, 7.357771], [3.924088, 7.355337], [3.936435, 7.338191]]]}, "properties": {"GID_0": "NGA", "NAME_0": "Nigeria", "GID_1": "NGA.31_1", "NAME_1": "Oyo", "NL_NAME_1": "", "GID_2": "NGA.31.9_1", "NAME_2": "IbadanSouth-East", "VARNAME_2": "Ibadan South-East", "NL_NAME_2": "", "TYPE_2": "Local Authority", "ENGTYPE_2": "Local Authority", "CC_2": "", "HASC_2": ""}}]}