{"type": "FeatureCollection", "features": [{"type": "Feature", "geometry": {"type": "Polygon", "coordinates": [[[121.278481, 14.51372], [121.255241, 14.51781], [121.253387, 14.54123], [121.256577, 14.55295], [121.260696, 14.56041], [121.263702, 14.57216], [121.29187, 14.5702], [121.290871, 14.56637], [121.297531, 14.54961], [121.296989, 14.53196], [121.291527, 14.52409], [121.278481, 14.51372]]]}, "properties": {"GID_0": "PHL", "NAME_0": "Philippines", "GID_1": "PHL.64_1", "NAME_1": "Rizal", "NL_NAME_1": "", "GID_2": "PHL.64.3_1", "NAME_2": "Baras", "VARNAME_2": "", "NL_NAME_2": "", "TYPE_2": "Bayan|Munisipyo", "ENGTYPE_2": "Municipality", "CC_2": "45803", "HASC_2": "PH.RI.BR"}}]}