{"type": "FeatureCollection", "features": [{"type": "Feature", "geometry": {"type": "Polygon", "coordinates": [[[44.099361, 56.322548], [44.095589, 56.323475], [44.097267, 56.325546], [44.100079, 56.325108], [44.099361, 56.322548]]]}, "properties": {"GID_0": "RUS", "NAME_0": "Russia", "GID_1": "RUS.47_1", "NAME_1": "Nizhegorod", "NL_NAME_1": "\u041d\u0438\u0436\u0435\u0433\u043e\u0440\u043e\u0434\u0441\u043a\u0430\u044f \u043e\u0431\u043b\u0430\u0441\u0442\u044c", "GID_2": "RUS.47.10_1", "NAME_2": "Bor", "VARNAME_2": "", "NL_NAME_2": "\u0411\u043e\u0440", "TYPE_2": "Gorod", "ENGTYPE_2": "City", "CC_2": "", "HASC_2": "RU.NZ.BG"}}]}