{"type": "FeatureCollection", "features": [{"type": "Feature", "geometry": {"type": "Polygon", "coordinates": [[[-49.118427, -20.603338], [-49.12986, -20.595316], [-49.199425, -20.535084], [-49.218674, -20.471046], [-49.17992, -20.474188], [-49.123055, -20.456684], [-49.086617, -20.416477], [-49.075226, -20.45146], [-49.004063, -20.526833], [-49.015556, -20.568642], [-48.990055, -20.581724], [-48.998837, -20.635139], [-49.118427, -20.603338]]]}, "properties": {"GID_0": "BRA", "NAME_0": "Brazil", "GID_1": "BRA.25_1", "NAME_1": "S\u00e3o Paulo", "NL_NAME_1": "", "GID_2": "BRA.25.11_1", "NAME_2": "Altair", "VARNAME_2": "", "NL_NAME_2": "", "TYPE_2": "Munic\u00edpio", "ENGTYPE_2": "Municipality", "CC_2": "", "HASC_2": ""}}]}