{"type": "FeatureCollection", "features": [{"type": "Feature", "geometry": {"type": "Polygon", "coordinates": [[[-51.175968, -22.738079], [-51.184017, -22.771521], [-51.155933, -22.848909], [-51.177444, -22.899923], [-51.215626, -22.961775], [-51.271854, -22.924847], [-51.315723, -22.91567], [-51.338165, -22.881922], [-51.317722, -22.830118], [-51.311787, -22.78513], [-51.34536, -22.714413], [-51.333225, -22.667501], [-51.296558, -22.671326], [-51.263729, -22.669044], [-51.211914, -22.724092], [-51.175968, -22.738079]]]}, "properties": {"GID_0": "BRA", "NAME_0": "Brazil", "GID_1": "BRA.16_1", "NAME_1": "Paran\u00e1", "NL_NAME_1": "", "GID_2": "BRA.16.9_1", "NAME_2": "Alvorada do Sul", "VARNAME_2": "", "NL_NAME_2": "", "TYPE_2": "Munic\u00edpio", "ENGTYPE_2": "Municipality", "CC_2": "", "HASC_2": ""}}]}