{"type": "FeatureCollection", "features": [{"type": "Feature", "geometry": {"type": "Polygon", "coordinates": [[[-39.203659, -4.046971], [-39.227612, -4.072559], [-39.323505, -4.089509], [-39.373425, -4.040724], [-39.443699, -3.970825], [-39.484909, -3.99993], [-39.484035, -3.973945], [-39.434887, -3.862872], [-39.391201, -3.883277], [-39.349529, -3.836803], [-39.309132, -3.935603], [-39.215187, -3.902105], [-39.184998, -3.938119], [-39.193439, -4.033066], [-39.203659, -4.046971]]]}, "properties": {"GID_0": "BRA", "NAME_0": "Brazil", "GID_1": "BRA.6_1", "NAME_1": "Cear\u00e1", "NL_NAME_1": "", "GID_2": "BRA.6.11_1", "NAME_2": "Apuiar\u00e9s", "VARNAME_2": "", "NL_NAME_2": "", "TYPE_2": "Munic\u00edpio", "ENGTYPE_2": "Municipality", "CC_2": "", "HASC_2": ""}}]}