{"type": "FeatureCollection", "features": [{"type": "Feature", "geometry": {"type": "Polygon", "coordinates": [[[-42.486584, -17.92659], [-42.521412, -17.947718], [-42.561218, -17.946856], [-42.572418, -17.98625], [-42.607243, -17.992807], [-42.644138, -17.923637], [-42.677803, -17.900484], [-42.644272, -17.777493], [-42.599972, -17.723148], [-42.615528, -17.769581], [-42.550056, -17.867203], [-42.556301, -17.900187], [-42.486584, -17.92659]]]}, "properties": {"GID_0": "BRA", "NAME_0": "Brazil", "GID_1": "BRA.13_1", "NAME_1": "Minas Gerais", "NL_NAME_1": "", "GID_2": "BRA.13.48_1", "NAME_2": "Aricanduva", "VARNAME_2": "", "NL_NAME_2": "", "TYPE_2": "Munic\u00edpio", "ENGTYPE_2": "Municipality", "CC_2": "", "HASC_2": ""}}]}