{"type": "FeatureCollection", "features": [{"type": "Feature", "geometry": {"type": "Polygon", "coordinates": [[[-44.017483, -20.053864], [-44.06234, -19.974787], [-44.030708, -19.976503], [-44.0172, -19.831656], [-43.976151, -19.781664], [-43.946156, -19.777264], [-43.862209, -19.827387], [-43.891598, -19.88533], [-43.871037, -19.928305], [-43.939762, -19.974928], [-43.992504, -20.029284], [-44.002171, -20.05739], [-44.017483, -20.053864]]]}, "properties": {"GID_0": "BRA", "NAME_0": "Brazil", "GID_1": "BRA.13_1", "NAME_1": "Minas Gerais", "NL_NAME_1": "", "GID_2": "BRA.13.65_1", "NAME_2": "Belo Horizonte", "VARNAME_2": "", "NL_NAME_2": "", "TYPE_2": "Munic\u00edpio", "ENGTYPE_2": "Municipality", "CC_2": "", "HASC_2": ""}}]}