{"type": "FeatureCollection", "features": [{"type": "Feature", "geometry": {"type": "Polygon", "coordinates": [[[-49.907555, -27.432425], [-49.956303, -27.402822], [-49.933514, -27.375282], [-49.940647, -27.335976], [-49.884518, -27.305964], [-49.84832, -27.327185], [-49.864422, -27.378143], [-49.907555, -27.432425]]]}, "properties": {"GID_0": "BRA", "NAME_0": "Brazil", "GID_1": "BRA.24_1", "NAME_1": "Santa Catarina", "NL_NAME_1": "", "GID_2": "BRA.24.46_1", "NAME_2": "Bra\u00e7o do Trombudo", "VARNAME_2": "", "NL_NAME_2": "", "TYPE_2": "Munic\u00edpio", "ENGTYPE_2": "Municipality", "CC_2": "", "HASC_2": ""}}]}