{"type": "FeatureCollection", "features": [{"type": "Feature", "geometry": {"type": "Polygon", "coordinates": [[[-49.267895, -22.492777], [-49.315788, -22.525389], [-49.452011, -22.575846], [-49.501728, -22.513639], [-49.48056, -22.507343], [-49.360897, -22.43326], [-49.316792, -22.387678], [-49.30032, -22.392324], [-49.267895, -22.492777]]]}, "properties": {"GID_0": "BRA", "NAME_0": "Brazil", "GID_1": "BRA.25_1", "NAME_1": "S\u00e3o Paulo", "NL_NAME_1": "", "GID_2": "BRA.25.95_1", "NAME_2": "Cabr\u00e1lia Paulista", "VARNAME_2": "", "NL_NAME_2": "", "TYPE_2": "Munic\u00edpio", "ENGTYPE_2": "Municipality", "CC_2": "", "HASC_2": ""}}]}