{"type": "FeatureCollection", "features": [{"type": "Feature", "geometry": {"type": "Polygon", "coordinates": [[[-37.843105, -6.333099], [-37.810333, -6.291669], [-37.757572, -6.290785], [-37.776348, -6.245804], [-37.749111, -6.193839], [-37.708988, -6.177279], [-37.646618, -6.189402], [-37.616169, -6.176493], [-37.612926, -6.270858], [-37.599907, -6.388227], [-37.577179, -6.420912], [-37.578682, -6.433967], [-37.73378, -6.390918], [-37.733295, -6.488269], [-37.742786, -6.465501], [-37.81823, -6.448353], [-37.795189, -6.366828], [-37.843105, -6.333099]]]}, "properties": {"GID_0": "BRA", "NAME_0": "Brazil", "GID_1": "BRA.15_1", "NAME_1": "Para\u00edba", "NL_NAME_1": "", "GID_2": "BRA.15.57_1", "NAME_2": "Catol\u00e9 do Rocha", "VARNAME_2": "", "NL_NAME_2": "", "TYPE_2": "Munic\u00edpio", "ENGTYPE_2": "Municipality", "CC_2": "", "HASC_2": ""}}]}