{"type": "FeatureCollection", "features": [{"type": "Feature", "geometry": {"type": "Polygon", "coordinates": [[[-41.322437, -3.179812], [-41.319111, -3.145363], [-41.256603, -3.088036], [-41.260731, -3.055087], [-41.249733, -3.029059], [-41.27227, -2.971292], [-41.19429, -2.998181], [-41.189598, -3.044543], [-41.15757, -3.070984], [-41.151073, -3.125136], [-41.237389, -3.180136], [-41.322437, -3.179812]]]}, "properties": {"GID_0": "BRA", "NAME_0": "Brazil", "GID_1": "BRA.6_1", "NAME_1": "Cear\u00e1", "NL_NAME_1": "", "GID_2": "BRA.6.46_1", "NAME_2": "Chaval", "VARNAME_2": "", "NL_NAME_2": "", "TYPE_2": "Munic\u00edpio", "ENGTYPE_2": "Municipality", "CC_2": "", "HASC_2": ""}}]}