{"type": "FeatureCollection", "features": [{"type": "Feature", "geometry": {"type": "Polygon", "coordinates": [[[-49.385029, -25.783558], [-49.455257, -25.786549], [-49.519302, -25.80706], [-49.614803, -25.781656], [-49.598843, -25.728804], [-49.608643, -25.635914], [-49.585823, -25.599848], [-49.547718, -25.60545], [-49.540791, -25.656197], [-49.477222, -25.638857], [-49.478115, -25.694963], [-49.4529, -25.731457], [-49.411999, -25.741831], [-49.385029, -25.783558]]]}, "properties": {"GID_0": "BRA", "NAME_0": "Brazil", "GID_1": "BRA.16_1", "NAME_1": "Paran\u00e1", "NL_NAME_1": "", "GID_2": "BRA.16.85_1", "NAME_2": "Contenda", "VARNAME_2": "", "NL_NAME_2": "", "TYPE_2": "Munic\u00edpio", "ENGTYPE_2": "Municipality", "CC_2": "", "HASC_2": ""}}]}