{"type": "FeatureCollection", "features": [{"type": "Feature", "geometry": {"type": "Polygon", "coordinates": [[[-35.683369, -6.659355], [-35.706955, -6.59986], [-35.689957, -6.591134], [-35.61628, -6.547791], [-35.558166, -6.546157], [-35.536594, -6.601987], [-35.576534, -6.607621], [-35.610237, -6.652609], [-35.660622, -6.636812], [-35.683369, -6.659355]]]}, "properties": {"GID_0": "BRA", "NAME_0": "Brazil", "GID_1": "BRA.15_1", "NAME_1": "Para\u00edba", "NL_NAME_1": "", "GID_2": "BRA.15.76_1", "NAME_2": "Dona In\u00eas", "VARNAME_2": "", "NL_NAME_2": "", "TYPE_2": "Munic\u00edpio", "ENGTYPE_2": "Municipality", "CC_2": "", "HASC_2": ""}}]}