{"type": "FeatureCollection", "features": [{"type": "Feature", "geometry": {"type": "Polygon", "coordinates": [[[-35.687481, -9.370838], [-35.713673, -9.354631], [-35.769264, -9.38846], [-35.768818, -9.308998], [-35.804352, -9.266531], [-35.836155, -9.264535], [-35.862171, -9.13742], [-35.812828, -9.162824], [-35.724735, -9.125352], [-35.692524, -9.284372], [-35.687481, -9.370838]]]}, "properties": {"GID_0": "BRA", "NAME_0": "Brazil", "GID_1": "BRA.2_1", "NAME_1": "Alagoas", "NL_NAME_1": "", "GID_2": "BRA.2.31_1", "NAME_2": "Flexeiras", "VARNAME_2": "", "NL_NAME_2": "", "TYPE_2": "Munic\u00edpio", "ENGTYPE_2": "Municipality", "CC_2": "", "HASC_2": ""}}]}