{"type": "FeatureCollection", "features": [{"type": "Feature", "geometry": {"type": "Polygon", "coordinates": [[[-44.1647, -5.70716], [-44.177097, -5.649885], [-44.121746, -5.589973], [-44.144382, -5.552135], [-44.195885, -5.544928], [-44.209373, -5.464329], [-44.206894, -5.464233], [-44.06778, -5.457562], [-44.07272, -5.436426], [-43.958443, -5.489055], [-43.992153, -5.508353], [-44.042912, -5.609168], [-44.114178, -5.642336], [-44.1647, -5.70716]]]}, "properties": {"GID_0": "BRA", "NAME_0": "Brazil", "GID_1": "BRA.10_1", "NAME_1": "Maranh\u00e3o", "NL_NAME_1": "", "GID_2": "BRA.10.80_1", "NAME_2": "Governador Luiz Rocha", "VARNAME_2": "", "NL_NAME_2": "", "TYPE_2": "Munic\u00edpio", "ENGTYPE_2": "Municipality", "CC_2": "", "HASC_2": ""}}]}