{"type": "FeatureCollection", "features": [{"type": "Feature", "geometry": {"type": "Polygon", "coordinates": [[[-39.2873, -14.692228], [-39.34322, -14.7243], [-39.407139, -14.711015], [-39.460773, -14.760616], [-39.510475, -14.733599], [-39.484035, -14.810805], [-39.530167, -14.807087], [-39.528919, -14.686156], [-39.510063, -14.547849], [-39.450577, -14.613625], [-39.2873, -14.692228]]]}, "properties": {"GID_0": "BRA", "NAME_0": "Brazil", "GID_1": "BRA.5_1", "NAME_1": "Bahia", "NL_NAME_1": "", "GID_2": "BRA.5.186_1", "NAME_2": "Itaju\u00edpe", "VARNAME_2": "", "NL_NAME_2": "", "TYPE_2": "Munic\u00edpio", "ENGTYPE_2": "Municipality", "CC_2": "", "HASC_2": ""}}]}