{"type": "FeatureCollection", "features": [{"type": "Feature", "geometry": {"type": "Polygon", "coordinates": [[[-39.366722, -4.725796], [-39.512966, -4.728325], [-39.579166, -4.747315], [-39.729248, -4.696853], [-39.738949, -4.652895], [-39.773579, -4.643512], [-39.741962, -4.600261], [-39.685535, -4.576072], [-39.687134, -4.556406], [-39.642792, -4.53926], [-39.57328, -4.471187], [-39.513271, -4.468898], [-39.443401, -4.575161], [-39.453777, -4.596017], [-39.366722, -4.725796]]]}, "properties": {"GID_0": "BRA", "NAME_0": "Brazil", "GID_1": "BRA.6_1", "NAME_1": "Cear\u00e1", "NL_NAME_1": "", "GID_2": "BRA.6.91_1", "NAME_2": "Itatira", "VARNAME_2": "", "NL_NAME_2": "", "TYPE_2": "Munic\u00edpio", "ENGTYPE_2": "Municipality", "CC_2": "", "HASC_2": ""}}]}