{"type": "FeatureCollection", "features": [{"type": "Feature", "geometry": {"type": "Polygon", "coordinates": [[[-51.539948, -27.238726], [-51.656754, -27.202026], [-51.66431, -27.202721], [-51.676422, -27.117958], [-51.618759, -27.041271], [-51.60186, -27.052092], [-51.558567, -27.109726], [-51.480652, -27.145279], [-51.539948, -27.238726]]]}, "properties": {"GID_0": "BRA", "NAME_0": "Brazil", "GID_1": "BRA.24_1", "NAME_1": "Santa Catarina", "NL_NAME_1": "", "GID_2": "BRA.24.137_1", "NAME_2": "Joa\u00e7aba", "VARNAME_2": "", "NL_NAME_2": "", "TYPE_2": "Munic\u00edpio", "ENGTYPE_2": "Municipality", "CC_2": "", "HASC_2": ""}}]}