{"type": "FeatureCollection", "features": [{"type": "Feature", "geometry": {"type": "Polygon", "coordinates": [[[-43.245003, -21.211958], [-43.269531, -21.278831], [-43.324974, -21.297119], [-43.372856, -21.285377], [-43.39323, -21.25672], [-43.443192, -21.250942], [-43.453831, -21.195793], [-43.417942, -21.158731], [-43.362118, -21.151213], [-43.35664, -21.096184], [-43.274609, -21.058132], [-43.243668, -21.084356], [-43.239635, -21.088188], [-43.275654, -21.193138], [-43.245003, -21.211958]]]}, "properties": {"GID_0": "BRA", "NAME_0": "Brazil", "GID_1": "BRA.13_1", "NAME_1": "Minas Gerais", "NL_NAME_1": "", "GID_2": "BRA.13.484_1", "NAME_2": "Merc\u00eas", "VARNAME_2": "", "NL_NAME_2": "", "TYPE_2": "Munic\u00edpio", "ENGTYPE_2": "Municipality", "CC_2": "", "HASC_2": ""}}]}