{"type": "FeatureCollection", "features": [{"type": "Feature", "geometry": {"type": "Polygon", "coordinates": [[[-61.742245, -11.333486], [-61.701027, -11.267904], [-61.666157, -11.258858], [-61.667011, -11.118427], [-61.632301, -11.118174], [-61.631943, -10.986303], [-61.550198, -10.986105], [-61.428944, -10.987543], [-61.426727, -11.113771], [-61.500061, -11.114336], [-61.501148, -11.333518], [-61.742245, -11.333486]]]}, "properties": {"GID_0": "BRA", "NAME_0": "Brazil", "GID_1": "BRA.22_1", "NAME_1": "Rond\u00f4nia", "NL_NAME_1": "", "GID_2": "BRA.22.25_1", "NAME_2": "Ministro Andreazza", "VARNAME_2": "", "NL_NAME_2": "", "TYPE_2": "Munic\u00edpio", "ENGTYPE_2": "Municipality", "CC_2": "", "HASC_2": ""}}]}