{"type": "FeatureCollection", "features": [{"type": "Feature", "geometry": {"type": "Polygon", "coordinates": [[[-41.704571, -15.508886], [-41.736965, -15.489451], [-41.757477, -15.420275], [-41.81797, -15.406628], [-41.846512, -15.413089], [-41.878693, -15.363791], [-41.854042, -15.338194], [-41.836208, -15.250776], [-41.778912, -15.254714], [-41.78577, -15.136386], [-41.800659, -15.101098], [-41.463875, -15.402158], [-41.362515, -15.494687], [-41.444294, -15.487006], [-41.504303, -15.526968], [-41.704571, -15.508886]]]}, "properties": {"GID_0": "BRA", "NAME_0": "Brazil", "GID_1": "BRA.13_1", "NAME_1": "Minas Gerais", "NL_NAME_1": "", "GID_2": "BRA.13.520_1", "NAME_2": "Ninheira", "VARNAME_2": "", "NL_NAME_2": "", "TYPE_2": "Munic\u00edpio", "ENGTYPE_2": "Municipality", "CC_2": "", "HASC_2": ""}}]}