{"type": "FeatureCollection", "features": [{"type": "Feature", "geometry": {"type": "Polygon", "coordinates": [[[-37.15184, -7.779856], [-37.138832, -7.74553], [-37.160927, -7.697973], [-37.114277, -7.640817], [-37.086941, -7.64339], [-37.085865, -7.59603], [-37.071026, -7.612198], [-37.035656, -7.635762], [-37.025364, -7.634105], [-37.025089, -7.717859], [-37.098022, -7.773207], [-37.15184, -7.779856]]]}, "properties": {"GID_0": "BRA", "NAME_0": "Brazil", "GID_1": "BRA.15_1", "NAME_1": "Para\u00edba", "NL_NAME_1": "", "GID_2": "BRA.15.151_1", "NAME_2": "Prata", "VARNAME_2": "", "NL_NAME_2": "", "TYPE_2": "Munic\u00edpio", "ENGTYPE_2": "Municipality", "CC_2": "", "HASC_2": ""}}]}