{"type": "FeatureCollection", "features": [{"type": "Feature", "geometry": {"type": "Polygon", "coordinates": [[[-46.958195, -0.862916], [-47.00676, -0.915108], [-46.99155, -0.995363], [-47.001949, -1.01165], [-47.012478, -1.013371], [-47.075375, -0.976194], [-47.06937, -0.941514], [-47.082359, -0.838194], [-47.029583, -0.766527], [-46.960693, -0.709029], [-46.935139, -0.853195], [-46.958195, -0.862916]]]}, "properties": {"GID_0": "BRA", "NAME_0": "Brazil", "GID_1": "BRA.14_1", "NAME_1": "Par\u00e1", "NL_NAME_1": "", "GID_2": "BRA.14.100_1", "NAME_2": "Quatipuru", "VARNAME_2": "", "NL_NAME_2": "", "TYPE_2": "Munic\u00edpio", "ENGTYPE_2": "Municipality", "CC_2": "", "HASC_2": ""}}]}