{"type": "FeatureCollection", "features": [{"type": "Feature", "geometry": {"type": "Polygon", "coordinates": [[[-53.410728, -26.949976], [-53.408344, -26.887968], [-53.374424, -26.875462], [-53.292168, -26.927816], [-53.284515, -27.007776], [-53.29546, -27.04582], [-53.33004, -27.087969], [-53.366169, -27.066559], [-53.376331, -27.013912], [-53.410728, -26.949976]]]}, "properties": {"GID_0": "BRA", "NAME_0": "Brazil", "GID_1": "BRA.24_1", "NAME_1": "Santa Catarina", "NL_NAME_1": "", "GID_2": "BRA.24.222_1", "NAME_2": "Riqueza", "VARNAME_2": "", "NL_NAME_2": "", "TYPE_2": "Munic\u00edpio", "ENGTYPE_2": "Municipality", "CC_2": "", "HASC_2": ""}}]}