{"type": "FeatureCollection", "features": [{"type": "Feature", "geometry": {"type": "Polygon", "coordinates": [[[-45.669361, -22.875868], [-45.736301, -22.890905], [-45.767551, -22.836489], [-45.770893, -22.805918], [-45.712467, -22.769054], [-45.676147, -22.787264], [-45.61422, -22.796457], [-45.633137, -22.841766], [-45.669361, -22.875868]]]}, "properties": {"GID_0": "BRA", "NAME_0": "Brazil", "GID_1": "BRA.25_1", "NAME_1": "S\u00e3o Paulo", "NL_NAME_1": "", "GID_2": "BRA.25.541_1", "NAME_2": "Santo Ant\u00f4nio do Pinhal", "VARNAME_2": "", "NL_NAME_2": "", "TYPE_2": "Munic\u00edpio", "ENGTYPE_2": "Municipality", "CC_2": "", "HASC_2": ""}}]}