{"type": "FeatureCollection", "features": [{"type": "Feature", "geometry": {"type": "Polygon", "coordinates": [[[-48.606083, -27.602083], [-48.629429, -27.637638], [-48.689285, -27.612692], [-48.738632, -27.614779], [-48.746029, -27.615513], [-48.727482, -27.553141], [-48.723022, -27.536776], [-48.680016, -27.522343], [-48.630695, -27.530895], [-48.600418, -27.572363], [-48.606083, -27.602083]]]}, "properties": {"GID_0": "BRA", "NAME_0": "Brazil", "GID_1": "BRA.24_1", "NAME_1": "Santa Catarina", "NL_NAME_1": "", "GID_2": "BRA.24.251_1", "NAME_2": "S\u00e3o Jos\u00e9", "VARNAME_2": "", "NL_NAME_2": "", "TYPE_2": "Munic\u00edpio", "ENGTYPE_2": "Municipality", "CC_2": "", "HASC_2": ""}}]}