{"type": "FeatureCollection", "features": [{"type": "Feature", "geometry": {"type": "Polygon", "coordinates": [[[-52.100178, -28.665459], [-52.155888, -28.651691], [-52.130192, -28.614567], [-52.171555, -28.598013], [-52.169476, -28.569384], [-52.235348, -28.548388], [-52.244247, -28.506172], [-52.211674, -28.48275], [-52.164814, -28.477615], [-52.088493, -28.495609], [-52.090191, -28.535658], [-52.092918, -28.615906], [-52.100178, -28.665459]]]}, "properties": {"GID_0": "BRA", "NAME_0": "Brazil", "GID_1": "BRA.21_1", "NAME_1": "Rio Grande do Sul", "NL_NAME_1": "", "GID_2": "BRA.21.461_1", "NAME_2": "Vila Maria", "VARNAME_2": "", "NL_NAME_2": "", "TYPE_2": "Munic\u00edpio", "ENGTYPE_2": "Municipality", "CC_2": "", "HASC_2": ""}}]}