{"type": "FeatureCollection", "features": [{"type": "Feature", "geometry": {"type": "Polygon", "coordinates": [[[21.686705, 41.98381], [21.67042, 41.960411], [21.67404, 41.934395], [21.631376, 41.941505], [21.582872, 41.919708], [21.572138, 41.950417], [21.532907, 41.968895], [21.540012, 41.987423], [21.588022, 42.000343], [21.633551, 42.040096], [21.688274, 42.009766], [21.686705, 41.98381]]]}, "properties": {"GID_0": "MKD", "NAME_0": "Macedonia", "GID_1": "MKD.28_1", "NAME_1": "Ilinden", "VARNAME_1": "", "NL_NAME_1": "", "TYPE_1": "Op\u0161tina", "ENGTYPE_1": "Municipality", "CC_1": "", "HASC_1": "MK.IL"}}]}