{"type": "FeatureCollection", "features": [{"type": "Feature", "geometry": {"type": "Polygon", "coordinates": [[[6.025593, 53.24015], [5.989357, 53.228645], [5.962276, 53.226967], [5.949005, 53.249454], [5.930977, 53.25132], [5.8876, 53.275711], [5.911807, 53.287289], [5.902916, 53.300781], [5.940727, 53.314995], [5.970941, 53.322052], [5.982795, 53.305847], [6.028011, 53.308338], [6.028216, 53.323593], [6.083936, 53.321526], [6.07753, 53.295532], [6.060892, 53.290234], [6.04969, 53.242725], [6.025593, 53.24015]]]}, "properties": {"GID_0": "NLD", "NAME_0": "Netherlands", "GID_1": "NLD.3_1", "NAME_1": "Friesland", "NL_NAME_1": "", "GID_2": "NLD.3.5_1", "NAME_2": "Dantumadeel", "VARNAME_2": "", "NL_NAME_2": "", "TYPE_2": "Gemeente", "ENGTYPE_2": "Municipality", "CC_2": "", "HASC_2": "NL.FR.DA"}}]}