{"type": "FeatureCollection", "features": [{"type": "Feature", "geometry": {"type": "Polygon", "coordinates": [[[5.931952, 52.391529], [5.918633, 52.387093], [5.88296, 52.358501], [5.872651, 52.359436], [5.828705, 52.390995], [5.82437, 52.401779], [5.777117, 52.39563], [5.763918, 52.406433], [5.796501, 52.422504], [5.82917, 52.445744], [5.848593, 52.470814], [5.883885, 52.45364], [5.876407, 52.443794], [5.905708, 52.421249], [5.931952, 52.391529]]]}, "properties": {"GID_0": "NLD", "NAME_0": "Netherlands", "GID_1": "NLD.4_1", "NAME_1": "Gelderland", "NL_NAME_1": "", "GID_2": "NLD.4.20_1", "NAME_2": "Elburg", "VARNAME_2": "", "NL_NAME_2": "", "TYPE_2": "Gemeente", "ENGTYPE_2": "Municipality", "CC_2": "", "HASC_2": "NL.GE.EL"}}]}