{"type": "FeatureCollection", "features": [{"type": "Feature", "geometry": {"type": "Polygon", "coordinates": [[[5.900457, 51.778423], [5.877406, 51.776859], [5.872875, 51.758923], [5.797226, 51.754673], [5.766692, 51.754757], [5.736277, 51.773682], [5.739219, 51.77906], [5.787273, 51.785221], [5.807728, 51.795937], [5.844212, 51.807491], [5.886461, 51.81094], [5.900457, 51.778423]]]}, "properties": {"GID_0": "NLD", "NAME_0": "Netherlands", "GID_1": "NLD.4_1", "NAME_1": "Gelderland", "NL_NAME_1": "", "GID_2": "NLD.4.32_1", "NAME_2": "Heumen", "VARNAME_2": "", "NL_NAME_2": "", "TYPE_2": "Gemeente", "ENGTYPE_2": "Municipality", "CC_2": "", "HASC_2": "NL.GE.HM"}}]}