{"type": "FeatureCollection", "features": [{"type": "Feature", "geometry": {"type": "Polygon", "coordinates": [[[5.465712, 51.772205], [5.521022, 51.796425], [5.542421, 51.817059], [5.563304, 51.827816], [5.604085, 51.828671], [5.643375, 51.820538], [5.669467, 51.795361], [5.699998, 51.789917], [5.718837, 51.776413], [5.698382, 51.7603], [5.656232, 51.764862], [5.584261, 51.746216], [5.58778, 51.732639], [5.539907, 51.741638], [5.504945, 51.73629], [5.504956, 51.746162], [5.465712, 51.772205]]]}, "properties": {"GID_0": "NLD", "NAME_0": "Netherlands", "GID_1": "NLD.8_1", "NAME_1": "Noord-Brabant", "NL_NAME_1": "", "GID_2": "NLD.8.47_1", "NAME_2": "Oss", "VARNAME_2": "", "NL_NAME_2": "", "TYPE_2": "Gemeente", "ENGTYPE_2": "Municipality", "CC_2": "", "HASC_2": "NL.NB.OS"}}]}