{"type": "FeatureCollection", "features": [{"type": "Feature", "geometry": {"type": "Polygon", "coordinates": [[[5.728713, 51.964897], [5.722972, 51.981964], [5.731862, 52.001694], [5.752457, 52.020496], [5.819776, 52.024799], [5.810841, 52.005077], [5.870712, 51.996807], [5.877827, 51.976139], [5.842742, 51.974461], [5.792955, 51.960247], [5.753583, 51.970226], [5.728713, 51.964897]]]}, "properties": {"GID_0": "NLD", "NAME_0": "Netherlands", "GID_1": "NLD.4_1", "NAME_1": "Gelderland", "NL_NAME_1": "", "GID_2": "NLD.4.49_1", "NAME_2": "Renkum", "VARNAME_2": "", "NL_NAME_2": "", "TYPE_2": "Gemeente", "ENGTYPE_2": "Municipality", "CC_2": "", "HASC_2": "NL.GE.RE"}}]}