{"type": "FeatureCollection", "features": [{"type": "Feature", "geometry": {"type": "Polygon", "coordinates": [[[35.737667, 32.083038], [35.704666, 32.080643], [35.742672, 32.169575], [35.834736, 32.168961], [35.815823, 32.113876], [35.737667, 32.083038]]]}, "properties": {"GID_0": "JOR", "NAME_0": "Jordan", "GID_1": "JOR.4_1", "NAME_1": "Balqa", "NL_NAME_1": "", "GID_2": "JOR.4.1_1", "NAME_2": "Al-Balqa", "VARNAME_2": "", "NL_NAME_2": "", "TYPE_2": "Nahia", "ENGTYPE_2": "Sub-Province", "CC_2": "", "HASC_2": ""}}]}