{"type": "FeatureCollection", "features": [{"type": "Feature", "geometry": {"type": "Polygon", "coordinates": [[[15.536178, 46.496387], [15.474832, 46.496323], [15.398053, 46.478466], [15.403318, 46.506916], [15.444388, 46.538956], [15.480154, 46.535439], [15.546766, 46.563953], [15.551591, 46.510628], [15.536178, 46.496387]]]}, "properties": {"GID_0": "SVN", "NAME_0": "Slovenia", "GID_1": "SVN.8_1", "NAME_1": "Podravska", "NL_NAME_1": "", "GID_2": "SVN.8.24_1", "NAME_2": "Ru\u0161e", "VARNAME_2": "", "NL_NAME_2": "", "TYPE_2": "Opcine", "ENGTYPE_2": "Commune|Municipality", "CC_2": "", "HASC_2": "SI.PD.RU"}}]}