{"type": "FeatureCollection", "features": [{"type": "Feature", "geometry": {"type": "Polygon", "coordinates": [[[-75.784103, 5.032401], [-75.831398, 4.9898], [-75.841698, 4.9529], [-75.811699, 4.917501], [-75.8498, 4.9171], [-75.906799, 4.920801], [-75.900551, 4.944449], [-75.898201, 5.001701], [-75.8395, 5.051099], [-75.803703, 5.050901], [-75.784103, 5.032401]]]}, "properties": {"GID_0": "COL", "NAME_0": "Colombia", "GID_1": "COL.7_1", "NAME_1": "Caldas", "NL_NAME_1": "", "GID_2": "COL.7.4_1", "NAME_2": "Belalc\u00e1zar", "VARNAME_2": "", "NL_NAME_2": "", "TYPE_2": "Municipio", "ENGTYPE_2": "Municipality", "CC_2": "", "HASC_2": "CO.CL.BE"}}]}