{"type": "FeatureCollection", "features": [{"type": "Feature", "geometry": {"type": "Polygon", "coordinates": [[[-74.0065, 4.336401], [-74.015198, 4.390701], [-74.009399, 4.403401], [-73.9991, 4.439799], [-73.9282, 4.440001], [-73.903397, 4.377601], [-73.913544, 4.324167], [-73.931, 4.349401], [-73.955803, 4.3529], [-74.0065, 4.336401]]]}, "properties": {"GID_0": "COL", "NAME_0": "Colombia", "GID_1": "COL.14_1", "NAME_1": "Cundinamarca", "NL_NAME_1": "", "GID_2": "COL.14.14_1", "NAME_2": "C\u00e1queza", "VARNAME_2": "", "NL_NAME_2": "", "TYPE_2": "Municipio", "ENGTYPE_2": "Municipality", "CC_2": "", "HASC_2": "CO.CU.CQ"}}]}