{"type": "FeatureCollection", "features": [{"type": "Feature", "geometry": {"type": "Polygon", "coordinates": [[[-77.830002, 1.0374], [-77.7798, 1.0615], [-77.744598, 1.021501], [-77.707199, 1.042701], [-77.724998, 0.9839], [-77.742302, 0.9799], [-77.765396, 0.9453], [-77.805702, 0.941401], [-77.821297, 0.9785], [-77.848999, 1.0034], [-77.830002, 1.0374]]]}, "properties": {"GID_0": "COL", "NAME_0": "Colombia", "GID_1": "COL.21_1", "NAME_1": "Nari\u00f1o", "NL_NAME_1": "", "GID_2": "COL.21.22_1", "NAME_2": "Guachucal", "VARNAME_2": "", "NL_NAME_2": "", "TYPE_2": "Municipio", "ENGTYPE_2": "Municipality", "CC_2": "", "HASC_2": "CO.NA.GC"}}]}