{"type": "FeatureCollection", "features": [{"type": "Feature", "geometry": {"type": "Polygon", "coordinates": [[[-77.601028, 0.909128], [-77.632202, 0.9315], [-77.641403, 0.985201], [-77.623001, 0.9898], [-77.578003, 0.9752], [-77.578003, 0.962401], [-77.601028, 0.909128]]]}, "properties": {"GID_0": "COL", "NAME_0": "Colombia", "GID_1": "COL.21_1", "NAME_1": "Nari\u00f1o", "NL_NAME_1": "", "GID_2": "COL.21.24_1", "NAME_2": "Gualmat\u00e1n", "VARNAME_2": "", "NL_NAME_2": "", "TYPE_2": "Municipio", "ENGTYPE_2": "Municipality", "CC_2": "", "HASC_2": "CO.NA.GM"}}]}