{"type": "FeatureCollection", "features": [{"type": "Feature", "geometry": {"type": "Polygon", "coordinates": [[[-77.552902, 1.460301], [-77.567299, 1.439501], [-77.592697, 1.438501], [-77.616898, 1.458801], [-77.657303, 1.452599], [-77.677498, 1.4689], [-77.746597, 1.4859], [-77.769096, 1.5004], [-77.800903, 1.5497], [-77.847, 1.5539], [-77.817001, 1.591301], [-77.785896, 1.602199], [-77.777802, 1.5796], [-77.699402, 1.533101], [-77.663696, 1.527701], [-77.614098, 1.4998], [-77.597298, 1.4778], [-77.552902, 1.460301]]]}, "properties": {"GID_0": "COL", "NAME_0": "Colombia", "GID_1": "COL.21_1", "NAME_1": "Nari\u00f1o", "NL_NAME_1": "", "GID_2": "COL.21.30_1", "NAME_2": "La Llanada", "VARNAME_2": "", "NL_NAME_2": "", "TYPE_2": "Municipio", "ENGTYPE_2": "Municipality", "CC_2": "", "HASC_2": "CO.NA.LL"}}]}