{"type": "FeatureCollection", "features": [{"type": "Feature", "geometry": {"type": "Polygon", "coordinates": [[[-73.3853, 5.5936], [-73.394501, 5.586099], [-73.446404, 5.593301], [-73.460197, 5.613501], [-73.486572, 5.658776], [-73.464798, 5.6754], [-73.392929, 5.630946], [-73.3853, 5.5936]]]}, "properties": {"GID_0": "COL", "NAME_0": "Colombia", "GID_1": "COL.6_1", "NAME_1": "Boyac\u00e1", "NL_NAME_1": "", "GID_2": "COL.6.56_1", "NAME_2": "Motavita", "VARNAME_2": "", "NL_NAME_2": "", "TYPE_2": "Municipio", "ENGTYPE_2": "Municipality", "CC_2": "", "HASC_2": "CO.BY.MV"}}]}