{"type": "FeatureCollection", "features": [{"type": "Feature", "geometry": {"type": "Polygon", "coordinates": [[[-78.635681, 15.856689], [-78.638611, 15.856506], [-78.636108, 15.862305], [-78.633301, 15.862487], [-78.635681, 15.856689]]]}, "properties": {"GID_0": "COL", "NAME_0": "Colombia", "GID_1": "COL.26_1", "NAME_1": "San Andr\u00e9s y Providencia", "NL_NAME_1": "", "GID_2": "COL.26.1_1", "NAME_2": "n.a. (1)", "VARNAME_2": "", "NL_NAME_2": "", "TYPE_2": "", "ENGTYPE_2": "", "CC_2": "", "HASC_2": ""}}]}