{"type": "FeatureCollection", "features": [{"type": "Feature", "geometry": {"type": "Polygon", "coordinates": [[[-72.920502, 6.3593], [-72.915298, 6.424], [-72.893501, 6.4828], [-72.905602, 6.5094], [-72.861801, 6.541], [-72.837601, 6.511501], [-72.830597, 6.4392], [-72.832298, 6.3988], [-72.893997, 6.3575], [-72.920502, 6.3593]]]}, "properties": {"GID_0": "COL", "NAME_0": "Colombia", "GID_1": "COL.27_1", "NAME_1": "Santander", "NL_NAME_1": "", "GID_2": "COL.27.71_1", "NAME_2": "San Joaqu\u00edn", "VARNAME_2": "", "NL_NAME_2": "", "TYPE_2": "Municipio", "ENGTYPE_2": "Municipality", "CC_2": "", "HASC_2": "CO.ST.SQ"}}]}