{"type": "FeatureCollection", "features": [{"type": "Feature", "geometry": {"type": "Polygon", "coordinates": [[[-74.119598, 5.5857], [-74.188805, 5.591179], [-74.198601, 5.617799], [-74.185997, 5.658199], [-74.1698, 5.670201], [-74.185997, 5.711301], [-74.172798, 5.747701], [-74.1157, 5.744501], [-74.075897, 5.700999], [-74.088501, 5.6324], [-74.119598, 5.5857]]]}, "properties": {"GID_0": "COL", "NAME_0": "Colombia", "GID_1": "COL.6_1", "NAME_1": "Boyac\u00e1", "NL_NAME_1": "", "GID_2": "COL.6.85_1", "NAME_2": "San Pablo de Borbur", "VARNAME_2": "", "NL_NAME_2": "", "TYPE_2": "Municipio", "ENGTYPE_2": "Municipality", "CC_2": "", "HASC_2": "CO.BY.SP"}}]}