{"type": "FeatureCollection", "features": [{"type": "Feature", "geometry": {"type": "Polygon", "coordinates": [[[-72.849899, 5.849], [-72.813004, 5.894999], [-72.796898, 5.9446], [-72.752502, 5.944402], [-72.739197, 5.864101], [-72.7006, 5.831001], [-72.681503, 5.838402], [-72.645798, 5.877001], [-72.654404, 5.784001], [-72.741501, 5.7861], [-72.807198, 5.8032], [-72.832527, 5.819118], [-72.849899, 5.849]]]}, "properties": {"GID_0": "COL", "NAME_0": "Colombia", "GID_1": "COL.6_1", "NAME_1": "Boyac\u00e1", "NL_NAME_1": "", "GID_2": "COL.6.104_1", "NAME_2": "Tasco", "VARNAME_2": "", "NL_NAME_2": "", "TYPE_2": "Municipio", "ENGTYPE_2": "Municipality", "CC_2": "", "HASC_2": "CO.BY.TA"}}]}