{"type": "FeatureCollection", "features": [{"type": "Feature", "geometry": {"type": "Polygon", "coordinates": [[[-74.147102, 5.226502], [-74.188599, 5.212802], [-74.219101, 5.177701], [-74.236397, 5.2026], [-74.229599, 5.253999], [-74.237099, 5.272], [-74.248596, 5.294502], [-74.233597, 5.331401], [-74.19532, 5.274821], [-74.185699, 5.249202], [-74.147102, 5.226502]]]}, "properties": {"GID_0": "COL", "NAME_0": "Colombia", "GID_1": "COL.14_1", "NAME_1": "Cundinamarca", "NL_NAME_1": "", "GID_2": "COL.14.109_1", "NAME_2": "Villag\u00f3mez", "VARNAME_2": "", "NL_NAME_2": "", "TYPE_2": "Municipio", "ENGTYPE_2": "Municipality", "CC_2": "", "HASC_2": "CO.CU.VG"}}]}