{"type": "FeatureCollection", "features": [{"type": "Feature", "geometry": {"type": "Polygon", "coordinates": [[[68.920067, 36.281643], [68.962524, 36.397743], [69.223549, 36.302715], [69.345085, 36.219841], [69.44091, 36.249603], [69.412994, 36.151741], [69.157295, 36.097294], [69.005226, 36.180882], [68.920067, 36.281643]]]}, "properties": {"GID_0": "AFG", "NAME_0": "Afghanistan", "GID_1": "AFG.3_1", "NAME_1": "Baghlan", "NL_NAME_1": "", "GID_2": "AFG.3.4_1", "NAME_2": "Burka", "VARNAME_2": "", "NL_NAME_2": "", "TYPE_2": "Wuleswali", "ENGTYPE_2": "District", "CC_2": "", "HASC_2": "AF.BL.BU"}}]}