{"type": "FeatureCollection", "features": [{"type": "Feature", "geometry": {"type": "Polygon", "coordinates": [[[69.468994, 35.02253], [69.527946, 35.06921], [69.550438, 35.158436], [69.552589, 35.159191], [69.729324, 35.158813], [69.78727, 35.098049], [69.815544, 35.047485], [69.69146, 34.935707], [69.61068, 34.938236], [69.468994, 35.02253]]]}, "properties": {"GID_0": "AFG", "NAME_0": "Afghanistan", "GID_1": "AFG.16_1", "NAME_1": "Kapisa", "NL_NAME_1": "", "GID_2": "AFG.16.5_1", "NAME_2": "Nijrab", "VARNAME_2": "", "NL_NAME_2": "", "TYPE_2": "Wuleswali", "ENGTYPE_2": "District", "CC_2": "", "HASC_2": "AF.KP.NI"}}]}