{"type": "FeatureCollection", "features": [{"type": "Feature", "geometry": {"type": "Polygon", "coordinates": [[[62.938446, 33.983982], [62.854893, 34.060001], [62.686069, 34.036221], [62.507046, 34.082363], [62.442261, 34.274216], [62.582996, 34.396587], [62.873901, 34.360611], [62.967613, 34.407043], [62.96928, 34.304565], [63.018581, 34.228001], [63.008553, 34.093002], [62.938446, 33.983982]]]}, "properties": {"GID_0": "AFG", "NAME_0": "Afghanistan", "GID_1": "AFG.12_1", "NAME_1": "Hirat", "NL_NAME_1": "", "GID_2": "AFG.12.14_1", "NAME_2": "Pashtun Zarghun", "VARNAME_2": "", "NL_NAME_2": "", "TYPE_2": "Wuleswali", "ENGTYPE_2": "District", "CC_2": "", "HASC_2": "AF.HR.PZ"}}]}