{"type": "FeatureCollection", "features": [{"type": "Feature", "geometry": {"type": "Polygon", "coordinates": [[[68.065872, 35.490612], [68.195061, 35.606441], [68.204681, 35.610695], [68.56102, 35.446476], [68.761124, 35.407169], [68.852516, 35.277203], [68.801598, 35.265099], [68.65097, 35.131172], [68.56739, 35.107079], [68.520134, 35.073677], [68.266212, 35.075546], [68.170074, 35.02784], [68.109406, 35.08065], [68.072708, 35.210186], [68.118172, 35.33522], [68.065872, 35.490612]]]}, "properties": {"GID_0": "AFG", "NAME_0": "Afghanistan", "GID_1": "AFG.3_1", "NAME_1": "Baghlan", "NL_NAME_1": "", "GID_2": "AFG.3.12_1", "NAME_2": "Tala Wa Barfak", "VARNAME_2": "", "NL_NAME_2": "", "TYPE_2": "Wuleswali", "ENGTYPE_2": "District", "CC_2": "", "HASC_2": "AF.BL.TB"}}]}