{"type": "FeatureCollection", "features": [{"type": "Feature", "geometry": {"type": "Polygon", "coordinates": [[[102.145882, 47.01009], [102.081078, 47.086048], [102.353638, 47.548325], [102.777351, 47.56057], [102.714088, 47.413288], [102.723366, 47.278183], [102.588188, 47.128647], [102.466759, 46.928944], [102.145882, 47.01009]]]}, "properties": {"GID_0": "MNG", "NAME_0": "Mongolia", "GID_1": "MNG.1_1", "NAME_1": "Arhangay", "NL_NAME_1": "", "GID_2": "MNG.1.11_1", "NAME_2": "Khotont", "VARNAME_2": "Hotont", "NL_NAME_2": "\u0425\u043e\u0442\u043e\u043d\u0442", "TYPE_2": "Soum", "ENGTYPE_2": "Sum", "CC_2": "", "HASC_2": "MN.AR.HO"}}]}